.codecov.yml
.pylintrc
.readthedocs.yml
AUTHORS
ChangeLog
Dockerfile.chewie
Dockerfile.freeradius
Dockerfile.fuzz
Dockerfile.wpasupplicant
LICENSE
README.md
build_docs.sh
codecheck-requirements.txt
docker-compose.yaml
fuzz-requirements.txt
requirements.txt
run_tests.sh
setup.cfg
setup.py
test-requirements.txt
.github/dependabot.yml
.github/workflows/release-docker.yml
.github/workflows/release-python.yml
.github/workflows/tests-codecheck.yml
.github/workflows/tests-integration.yml
.github/workflows/tests-unit.yml
.github/workflows/tests-yaml-lint.yml
.github/workflows/disabled/release-debian.yml
c65chewie.egg-info/PKG-INFO
c65chewie.egg-info/SOURCES.txt
c65chewie.egg-info/dependency_links.txt
c65chewie.egg-info/entry_points.txt
c65chewie.egg-info/not-zip-safe
c65chewie.egg-info/pbr.json
c65chewie.egg-info/requires.txt
c65chewie.egg-info/top_level.txt
chewie/__init__.py
chewie/__main__.py
chewie/auth_8021x.py
chewie/chewie.py
chewie/eap.py
chewie/ethernet_packet.py
chewie/event.py
chewie/mac_address.py
chewie/message_parser.py
chewie/nfv_sockets.py
chewie/radius.py
chewie/radius_attributes.py
chewie/radius_datatypes.py
chewie/radius_lifecycle.py
chewie/radius_socket.py
chewie/timer_scheduler.py
chewie/utils.py
chewie/state_machines/__init__.py
chewie/state_machines/abstract_state_machine.py
chewie/state_machines/eap_state_machine.py
chewie/state_machines/mab_state_machine.py
debian/README.source
debian/changelog
debian/compat
debian/control
debian/copyright
debian/rules
debian/source/format
docker/fuzz_packet.sh
docker/pip_deps.sh
docker/retrycmd.sh
docker/run_integration_tests.sh
docs/Makefile
docs/architecture.rst
docs/conf.py
docs/development.rst
docs/index.rst
docs/intro.rst
docs/requirements.txt
etc/freeradius/clients.conf
etc/freeradius/users
etc/freeradius/certs/01.pem
etc/freeradius/certs/02.pem
etc/freeradius/certs/Makefile
etc/freeradius/certs/README
etc/freeradius/certs/bootstrap
etc/freeradius/certs/ca.cnf
etc/freeradius/certs/ca.der
etc/freeradius/certs/ca.key
etc/freeradius/certs/ca.pem
etc/freeradius/certs/client.cnf
etc/freeradius/certs/client.crt
etc/freeradius/certs/client.csr
etc/freeradius/certs/client.key
etc/freeradius/certs/client.p12
etc/freeradius/certs/client.pem
etc/freeradius/certs/dh
